[
  {
    "num": 1,
    "track_name": "Seven_(feat._Latto)_(Explicit_Ver.)",
    "artist_name": "Latto,_Jung_Kook",
    "lanch": "2023-7-14",
    "in_spotify_playlists": 553,
    "in_spotify_charts": 147,
    "streams": "141381703",
    "danceability": 80,
    "valence": 89,
    "energy": 83,
    "acousticness": 31,
    "instrumentalness": 0,
    "liveness": 8,
    "speechiness": 4,
    "slug":"song1"
  },
  {
    "id": 2,
    "track_name": "LALA",
    "artist_name": "Myke_Towers",
    "lanch": "2023-3-23",
    "in_spotify_playlists": 1474,
    "in_spotify_charts": 48,
    "streams": "133716286",
    "danceability": 71,
    "valence": 61,
    "energy": 74,
    "acousticness": 7,
    "instrumentalness": 0,
    "liveness": 10,
    "speechiness": 4,
    "slug":"song2"
  },
  {
    "id": 3,
    "track_name": "vampire",
    "artist_name": "Olivia_Rodrigo",
    "lanch": "2023-6-30",
    "in_spotify_playlists": 1397,
    "in_spotify_charts": 113,
    "streams": "140003974",
    "danceability": 51,
    "valence": 32,
    "energy": 53,
    "acousticness": 17,
    "instrumentalness": 0,
    "liveness": 31,
    "speechiness": 6,
    "slug":"song3"
  },
  {
    "id": 4,
    "track_name": "Cruel_Summer",
    "artist_name": "Taylor_Swift",
    "lanch": "2019-8-23",
    "in_spotify_playlists": 7858,
    "in_spotify_charts": 100,
    "streams": "800840817",
    "danceability": 55,
    "valence": 58,
    "energy": 72,
    "acousticness": 11,
    "instrumentalness": 0,
    "liveness": 11,
    "speechiness": 15,
    "slug":"song4"
  },
  {
    "id": 5,
    "track_name": "WHERE_SHE_GOES",
    "artist_name": "Bad_Bunny",
    "lanch": "2023-5-18",
    "in_spotify_playlists": 3133,
    "in_spotify_charts": 50,
    "streams": "303236322",
    "danceability": 65,
    "valence": 23,
    "energy": 80,
    "acousticness": 14,
    "instrumentalness": 63,
    "liveness": 11,
    "speechiness": 6,
    "slug":"song5"
  },
  {
    "id": 6,
    "track_name": "Sprinter",
    "artist_name": "Dave,_Central_Cee",
    "lanch": "2023-6-1",
    "in_spotify_playlists": 2186,
    "in_spotify_charts": 91,
    "streams": "183706234",
    "danceability": 92,
    "valence": 66,
    "energy": 58,
    "acousticness": 19,
    "instrumentalness": 0,
    "liveness": 8,
    "speechiness": 24,
    "slug":"song6"
  },
  {
    "id": 7,
    "track_name": "Ella_Baila_Sola",
    "artist_name": "Eslabon_Armado,_Peso_Pluma",
    "lanch": "2023-3-16",
    "in_spotify_playlists": 3090,
    "in_spotify_charts": 50,
    "streams": "725980112",
    "danceability": 67,
    "valence": 83,
    "energy": 76,
    "acousticness": 48,
    "instrumentalness": 0,
    "liveness": 8,
    "speechiness": 3,
    "slug":"song7"
  },
  {
    "id": 8,
    "track_name": "Columbia",
    "artist_name": "Quevedo",
    "lanch": "2023-7-7",
    "in_spotify_playlists": 714,
    "in_spotify_charts": 43,
    "streams": "58149378",
    "danceability": 67,
    "valence": 26,
    "energy": 71,
    "acousticness": 37,
    "instrumentalness": 0,
    "liveness": 11,
    "speechiness": 4,
    "slug":"song8"
  },
  {
    "id": 9,
    "track_name": "fukumean",
    "artist_name": "Gunna",
    "lanch": "2023-5-15",
    "in_spotify_playlists": 1096,
    "in_spotify_charts": 83,
    "streams": "95217315",
    "danceability": 85,
    "valence": 22,
    "energy": 62,
    "acousticness": 12,
    "instrumentalness": 0,
    "liveness": 28,
    "speechiness": 9,
    "slug":"song9"
  },
  {
    "id": 10,
    "track_name": "La_Bebe_-_Remix",
    "artist_name": "Peso_Pluma,_Yng_Lvcas",
    "lanch": "2023-3-17",
    "in_spotify_playlists": 2953,
    "in_spotify_charts": 44,
    "streams": "553634067",
    "danceability": 81,
    "valence": 56,
    "energy": 48,
    "acousticness": 21,
    "instrumentalness": 0,
    "liveness": 8,
    "speechiness": 33,
    "slug":"song10"
  },
  {
    "id": 11,
    "track_name": "un_x100to",
    "artist_name": "Bad_Bunny,_Grupo_Frontera",
    "lanch": "2023-4-17",
    "in_spotify_playlists": 2876,
    "in_spotify_charts": 40,
    "streams": "505671438",
    "danceability": 57,
    "valence": 56,
    "energy": 72,
    "acousticness": 23,
    "instrumentalness": 0,
    "liveness": 27,
    "speechiness": 5,
    "slug":"song11"
  },
  {
    "id": 12,
    "track_name": "Super_Shy",
    "artist_name": "NewJeans",
    "lanch": "2023-7-7",
    "in_spotify_playlists": 422,
    "in_spotify_charts": 55,
    "streams": "58255150",
    "danceability": 78,
    "valence": 52,
    "energy": 82,
    "acousticness": 18,
    "instrumentalness": 0,
    "liveness": 15,
    "speechiness": 7,
    "slug":"song12"
  },
  {
    "id": 13,
    "track_name": "Flowers",
    "artist_name": "Miley_Cyrus",
    "lanch": "2023-1-12",
    "in_spotify_playlists": 12211,
    "in_spotify_charts": 115,
    "streams": "1316855716",
    "danceability": 71,
    "valence": 65,
    "energy": 68,
    "acousticness": 6,
    "instrumentalness": 0,
    "liveness": 3,
    "speechiness": 7,
    "slug":"song13"
  },
  {
    "id": 14,
    "track_name": "Daylight",
    "artist_name": "David_Kushner",
    "lanch": "2023-4-14",
    "in_spotify_playlists": 3528,
    "in_spotify_charts": 98,
    "streams": "387570742",
    "danceability": 51,
    "valence": 32,
    "energy": 43,
    "acousticness": 83,
    "instrumentalness": 0,
    "liveness": 9,
    "speechiness": 3,
    "slug":"song14"
  },
  {
    "id": 15,
    "track_name": "As_It_Was",
    "artist_name": "Harry_Styles",
    "lanch": "2022-3-31",
    "in_spotify_playlists": 23575,
    "in_spotify_charts": 130,
    "streams": "2513188493",
    "danceability": 52,
    "valence": 66,
    "energy": 73,
    "acousticness": 34,
    "instrumentalness": 0,
    "liveness": 31,
    "speechiness": 6,
    "slug":"song15"
  },
  {
    "id": 16,
    "track_name": "Kill_Bill",
    "artist_name": "SZA",
    "lanch": "2022-12-8",
    "in_spotify_playlists": 8109,
    "in_spotify_charts": 77,
    "streams": "1163093654",
    "danceability": 64,
    "valence": 43,
    "energy": 73,
    "acousticness": 5,
    "instrumentalness": 17,
    "liveness": 16,
    "speechiness": 4,
    "slug":"song16"
  },
  {
    "id": 17,
    "track_name": "Cupid_-_Twin_Ver.",
    "artist_name": "Fifty_Fifty",
    "lanch": "2023-2-24",
    "in_spotify_playlists": 2942,
    "in_spotify_charts": 77,
    "streams": "496795686",
    "danceability": 78,
    "valence": 76,
    "energy": 59,
    "acousticness": 43,
    "instrumentalness": 0,
    "liveness": 34,
    "speechiness": 3,
    "slug":"song17"
  },
  {
    "id": 18,
    "track_name": "What_Was_I_Made_For?_[From_The_Motion_Picture_\"Barbie\"]",
    "artist_name": "Billie_Eilish",
    "lanch": "2023-7-13",
    "in_spotify_playlists": 873,
    "in_spotify_charts": 104,
    "streams": "30546883",
    "danceability": 44,
    "valence": 14,
    "energy": 9,
    "acousticness": 96,
    "instrumentalness": 0,
    "liveness": 10,
    "speechiness": 3,
    "slug":"song18"
  },
  {
    "id": 19,
    "track_name": "Classy_101",
    "artist_name": "Feid,_Young_Miko",
    "lanch": "2023-3-31",
    "in_spotify_playlists": 2610,
    "in_spotify_charts": 40,
    "streams": "335222234",
    "danceability": 86,
    "valence": 67,
    "energy": 66,
    "acousticness": 14,
    "instrumentalness": 0,
    "liveness": 12,
    "speechiness": 16,
    "slug":"song19"
  },
  {
    "id": 20,
    "track_name": "Like_Crazy",
    "artist_name": "Jimin",
    "lanch": "2023-3-24",
    "in_spotify_playlists": 596,
    "in_spotify_charts": 68,
    "streams": "363369738",
    "danceability": 63,
    "valence": 36,
    "energy": 73,
    "acousticness": 0,
    "instrumentalness": 0,
    "liveness": 36,
    "speechiness": 4,
    "slug":"song20"
  }
]